{"article_xxg传.md":"BAQTOJwL","article_nellywidthplugin传.md":"4LVaIPko","article_♡传.md":"BVz-DHDK","article_zailyn.md":"DLUM19tb","article_earth.md":"C9-7cYIe","article_世人价传.md":"Cg4tfmpf","article_微篇集合.md":"CrBzOwN-","test.md":"D0DrL4EL","article_也好传.md":"DaHZWMWA","article_二人传.md":"DV4Dcdhw","article_橘子树传.md":"CjXFMQ2A","article_天才少女传.md":"B0110i0d","article_闪星传.md":"CoYjTlUP","article_鲸鱼传.md":"D8F-ymfJ","index.md":"BR60gRpp","article_忍冬藤传.md":"Qlkk-VJY","article_steve传.md":"ITypkurQ","article_kungianka传.md":"CtpPD_Sw","article_贡献与鸣谢.md":"q3U9k_v-","article_buku传.md":"KdPayUr4","article_土皇帝喵.md":"BQsbUE7r","article_真大瓜.md":"D-JD8YZr","nav_index.md":"CFOzDcve","article_青柠传.md":"CvWMsgRe","article_pankuler传.md":"C3SXzvev","article_月亮先生传.md":"C_nl-nuk","article_袁纸列传.md":"CU3732Eh","article_程杰列传.md":"-tltYSls","article_影传.md":"DdXG_Mnf","article_我传.md":"KfeuqhCv","article_tinksp管理an.md":"BNm3xU3L","article_小友老师.md":"Cb8nFNCX","article_版主米饭传.md":"BGd_mn0m","article_nicehello传.md":"CKrg3ovt","article_留白传.md":"B3np7V1_"}
